devtools_hex_ascii/__init__.py
devtools_hex_ascii-1.0.1.dist-info/METADATA
devtools_hex_ascii-1.0.1.dist-info/WHEEL
devtools_hex_ascii-1.0.1.dist-info/top_level.txt
devtools_hex_ascii-1.0.1.dist-info/RECORD
