Metadata-Version: 2.1
Name: devtools-hex-ascii
Version: 1.0.1
Summary: Hex to ASCII converter
Home-page: https://devtools.at/tools/hex-ascii
Author: DevTools.at
Author-email: hello@devtools.at
Project-URL: Homepage, https://devtools.at/tools/hex-ascii
Project-URL: Repository, https://github.com/devtools-at/hex-ascii
Classifier: Development Status :: 4 - Beta
Classifier: Intended Audience :: Developers
Classifier: License :: OSI Approved :: MIT License
Classifier: Programming Language :: Python :: 3
Requires-Python: >=3.8
